{
    "portfolio": [
        {
            "cover": "/portfolio/kratos.jpg",
            "title": "God of War",
            "description": "JavaScript SCSS WebPack",
            "url": "https://ragnarok-godofwar.netlify.app/"
        },
        {
            "cover": "/portfolio/new-collection.png",
            "title": "Furniro",
            "description": "React TypeScript Tailwind",
            "url": "https://web-furniro.netlify.app/"
        },
        {
            "cover": "/portfolio/stuff.jpg",
            "title": "Stuff Shop",
            "description": "React Redux Toolkit CSS Axios",
            "url": "https://stuff-shop.netlify.app/"
        },
        {
            "cover": "/portfolio/marvel.jpg",
            "title": "Marvel",
            "description": "React JavaScript SASS Formik",
            "url": "https://thrillu4.github.io/marvel-project/"
        },
        {
            "cover": "/portfolio/evogym.png",
            "title": "Evo Gym",
            "description": "React Vite TypeScript Tailwind",
            "url": "https://de0f1faf.fitness-gym-application.pages.dev/"
        },
        {
            "cover": "/portfolio/dat-shop.png",
            "title": "DAT Shop",
            "description": "React JavaScript SASS RouterDom v6",
            "url": "https://dat-shop.netlify.app/"
        },
        {
            "cover": "/portfolio/employees.jpeg",
            "title": "Employees List",
            "description": "React JavaScript SASS",
            "url": "https://employees-react-list.netlify.app/"
        },
        {
            "cover": "/portfolio/weather.jpg",
            "title": "Weather App",
            "description": "React JavaScript CSS API",
            "url": "https://weather-react-app-thrillu4.netlify.app/"
        }
    ]
}
